Workbook

Sheet Inputs
A1: Generic Solar PV — Inputs
A3: Project name | B3: string | C3: Generic Solar PV
A4: Company | B4: string | C4: SolarCo
A5: Code | B5: string | C5: SOLAR-001
A6: Country | B6: ISO | C6: DE
A7: Financial close | B7: date | C7: 47484
A8: COD date | B8: date | C8: 47849
A9: Construction months | B9: months | C9: 12
A10: Horizon years | B10: years | C10: 25
A11: Capacity MW | B11: MW | C11: 50
A12: Operating hours P50 | B12: hrs/yr | C12: 1500
A13: PV degradation /yr | B13: % | C13: 0.004
A14: Plant availability | B14: ratio | C14: 0.9801
A15: PPA base tariff | B15: EUR/MWh | C15: 55
A16: PPA term years | B16: years | C16: 10
A17: PPA indexation /yr | B17: % | C17: 0.02
A18: Market price Y1 | B18: EUR/MWh | C18: 60
... A21: Balancing cost | B21: EUR/MWh | C21: 0
A22: CO2 enabled | B22: bool | C22: FALSE
A23: CO2 price | B23: EUR/MWh | C23: 0
A24: Annual OPEX inflation | B24: % | C24: 0.02
A25: Share capital | B25: kEUR | C25: 500
A26: SHL amount | B26: kEUR | C26: 5000
A27: SHL rate | B27: % | C27: 0.08
A28: Gearing cap | B28: ratio | C28: 0.75
A29: Senior tenor years | B29: years | C29: 15
A30: Base rate | B30: % | C30: 0.03
A31: Margin bps | B31: bps | C31: 250
A32: Target DSCR | B32: x | C32: 1.2
A33: Corporate tax rate | B33: % | C33: 0.25
A34: Loss carryforward years | B34: years | C34: 5
... A37: Depreciation life | B37: years | C37: 20

Sheet CapEx
A1: Generic Solar PV — CapEx Schedule (kEUR)
A3: Period | B3: Profile | C3: P1 | D3: P2 | E3: P3 | F3: P4 | G3: P5 | H3: P6 | I3: P7 | J3: P8 | K3: P9 | L3: P10 | M3: P11 | N3: P12 | O3: P13 | P3: P14 | Q3: P15 | R3: P16 | S3: P17 | T3: P18 | U3: P19 | V3: P20 | W3: P21 | X3: P22 | Y3: P23 | Z3: P24 | AA3: P25 | AB3: P26 | AC3: P27 | AD3: P28 | AE3: P29 | AF3: P30 | AG3: P31 | AH3: P32 | AI3: P33 | AJ3: P34 | AK3: P35 | AL3: P36 | AM3: P37 | AN3: P38 | AO3: P39 | AP3: P40 | AQ3: P41 | AR3: P42 | AS3: P43 | AT3: P44 | AU3: P45 | AV3: P46 | AW3: P47 | AX3: P48 | AY3: P49 | AZ3: P50 | BA3: P51 | BB3: P52
A4: Period end date | C4: 47665 | D4: 47849 | E4: 48030 | F4: 48214 | G4: 48396 | H4: 48580 | I4: 48761 | J4: 48945 | K4: 49126 | L4: 49310 | M4: 49491 | N4: 49675 | O4: 49857 | P4: 50041 | Q4: 50222 | R4: 50406 | S4: 50587 | T4: 50771 | U4: 50952 | V4: 51136 | W4: 51318 | X4: 51502 | Y4: 51683 | Z4: 51867 | AA4: 52048 | AB4: 52232 | AC4: 52413 | AD4: 52597 | AE4: 52779 | AF4: 52963 | AG4: 53144 | AH4: 53328 | AI4: 53509 | AJ4: 53693 | AK4: 53874 | AL4: 54058 | AM4: 54240 | AN4: 54424 | AO4: 54605 | AP4: 54789 | AQ4: 54970 | AR4: 55154 | AS4: 55335 | AT4: 55519 | AU4: 55701 | AV4: 55885 | AW4: 56066 | AX4: 56250 | AY4: 56431 | AZ4: 56615 | BA4: 56796 | BB4: 56980
BD5: Item Total (kEUR)
A6: Solar Modules | B6: kEUR | C6: =0.5*$BD$6 -> 10000 | D6: =0.5*$BD$6 -> 10000 | E6: =0.0*$BD$6 -> 0 | F6: =0.0*$BD$6 -> 0 | G6: =0.0*$BD$6 -> 0 | H6: =0.0*$BD$6 -> 0 | I6: =0.0*$BD$6 -> 0 | J6: =0.0*$BD$6 -> 0 | K6: =0.0*$BD$6 -> 0 | L6: =0.0*$BD$6 -> 0 | ... BB6: =0.0*$BD$6 -> 0 | BD6: 20000
A7: Inverters | B7: kEUR | C7: =0.5*$BD$7 -> 1500 | D7: =0.5*$BD$7 -> 1500 | E7: =0.0*$BD$7 -> 0 | F7: =0.0*$BD$7 -> 0 | G7: =0.0*$BD$7 -> 0 | H7: =0.0*$BD$7 -> 0 | I7: =0.0*$BD$7 -> 0 | J7: =0.0*$BD$7 -> 0 | K7: =0.0*$BD$7 -> 0 | L7: =0.0*$BD$7 -> 0 | ... BB7: =0.0*$BD$7 -> 0 | BD7: 3000
A8: Civil Works | B8: kEUR | C8: =0.3*$BD$8 -> 1500 | D8: =0.7*$BD$8 -> 3500 | E8: =0.0*$BD$8 -> 0 | F8: =0.0*$BD$8 -> 0 | G8: =0.0*$BD$8 -> 0 | H8: =0.0*$BD$8 -> 0 | I8: =0.0*$BD$8 -> 0 | J8: =0.0*$BD$8 -> 0 | K8: =0.0*$BD$8 -> 0 | L8: =0.0*$BD$8 -> 0 | ... BB8: =0.0*$BD$8 -> 0 | BD8: 5000
A9: Grid Connection | B9: kEUR | C9: =0.5*$BD$9 -> 1000 | D9: =0.5*$BD$9 -> 1000 | E9: =0.0*$BD$9 -> 0 | F9: =0.0*$BD$9 -> 0 | G9: =0.0*$BD$9 -> 0 | H9: =0.0*$BD$9 -> 0 | I9: =0.0*$BD$9 -> 0 | J9: =0.0*$BD$9 -> 0 | K9: =0.0*$BD$9 -> 0 | L9: =0.0*$BD$9 -> 0 | ... BB9: =0.0*$BD$9 -> 0 | BD9: 2000
A10: Soft Costs | B10: kEUR | C10: =1.0*$BD$10 -> 3000 | D10: =0.0*$BD$10 -> 0 | E10: =0.0*$BD$10 -> 0 | F10: =0.0*$BD$10 -> 0 | G10: =0.0*$BD$10 -> 0 | H10: =0.0*$BD$10 -> 0 | I10: =0.0*$BD$10 -> 0 | J10: =0.0*$BD$10 -> 0 | K10: =0.0*$BD$10 -> 0 | ... BB10: =0.0*$BD$10 -> 0 | BD10: 3000
A11: Total Hard CapEx | C11: =SUM(C6:C10) -> 17000 | D11: =SUM(D6:D10) -> 16000 | E11: =SUM(E6:E10) -> 0 | F11: =SUM(F6:F10) -> 0 | G11: =SUM(G6:G10) -> 0 | H11: =SUM(H6:H10) -> 0 | I11: =SUM(I6:I10) -> 0 | J11: =SUM(J6:J10) -> 0 | ... BB11: =SUM(BB6:BB10) -> 0 | BD11: =SUM(BD6:BD10) -> 33000
A13: IDC | C13: ='IDC'!$C$30 -> 0
A14: Bank fees | C14: ='Inputs'!$C$36 -> 0
A16: TOTAL CAPEX (incl. IDC + fees) | C16: =BD11+C13+C14 -> 33000

Sheet IDC
A1: Generic Solar PV — IDC / Construction Drawdown
A3: Assumption: senior debt is drawn as a single bullet at COD, sized via DSCR sculpting (see Debt Service tab). Construction capex is funded 100% by equity, so no debt balance accrues interest during construction.
A5: Period | C5: P1 | D5: P2
A6: Construction debt drawdown (kEUR) | C6: 0 | D6: 0
A7: Opening construction debt balance (kEUR) | C7: 0 | D7: =C9 -> 0
A8: Interest rate per period | C8: =('Inputs'!$C$30+'Inputs'!$C$31/10000)/2 -> 0.0275 | D8: =('Inputs'!$C$30+'Inputs'!$C$31/10000)/2 -> 0.0275
A9: Closing construction debt balance (kEUR) | C9: =C7+C6 -> 0 | D9: =D7+D6 -> 0
A10: Interest during construction (kEUR) | C10: =C7*C8 -> 0 | D10: =D7*D8 -> 0
A30: TOTAL IDC (kEUR) | C30: =SUM(C10:D10) -> 0

Sheet OpEx
A1: Generic Solar PV — OpEx (kEUR)
A3: Period | C3: P1 | D3: P2 | E3: P3 | F3: P4 | G3: P5 | H3: P6 | I3: P7 | J3: P8 | K3: P9 | L3: P10 | M3: P11 | N3: P12 | O3: P13 | P3: P14 | Q3: P15 | R3: P16 | S3: P17 | T3: P18 | U3: P19 | V3: P20 | W3: P21 | X3: P22 | Y3: P23 | Z3: P24 | AA3: P25 | AB3: P26 | AC3: P27 | AD3: P28 | AE3: P29 | AF3: P30 | AG3: P31 | AH3: P32 | AI3: P33 | AJ3: P34 | AK3: P35 | AL3: P36 | AM3: P37 | AN3: P38 | AO3: P39 | AP3: P40 | AQ3: P41 | AR3: P42 | AS3: P43 | AT3: P44 | AU3: P45 | AV3: P46 | AW3: P47 | AX3: P48 | AY3: P49 | AZ3: P50 | BA3: P51 | BB3: P52
A4: Operating year | C4: - | D4: - | E4: 1 | F4: 1 | G4: 2 | H4: 2 | I4: 3 | J4: 3 | K4: 4 | L4: 4 | M4: 5 | N4: 5 | O4: 6 | P4: 6 | Q4: 7 | R4: 7 | S4: 8 | T4: 8 | U4: 9 | V4: 9 | W4: 10 | X4: 10 | Y4: 11 | Z4: 11 | AA4: 12 | AB4: 12 | AC4: 13 | AD4: 13 | AE4: 14 | AF4: 14 | AG4: 15 | AH4: 15 | AI4: 16 | AJ4: 16 | AK4: 17 | AL4: 17 | AM4: 18 | AN4: 18 | AO4: 19 | AP4: 19 | AQ4: 20 | AR4: 20 | AS4: 21 | AT4: 21 | AU4: 22 | AV4: 22 | AW4: 23 | AX4: 23 | AY4: 24 | AZ4: 24 | BA4: 25 | BB4: 25
BD5: Y1 Amount (kEUR)
A6: Technical Management | B6: kEUR | C6: 0 | D6: 0 | E6: =$BD$6/2*(1+'Inputs'!$C$24)^(1-1) -> 75 | F6: =$BD$6/2*(1+'Inputs'!$C$24)^(1-1) -> 75 | G6: =$BD$6/2*(1+'Inputs'!$C$24)^(2-1) -> 76.5 | H6: =$BD$6/2*(1+'Inputs'!$C$24)^(2-1) -> 76.5 | I6: =$BD$6/2*(1+'Inputs'!$C$24)^(3-1) -> 78.03 | J6: =$BD$6/2*(1+'Inputs'!$C$24)^(3-1) -> 78.03 | K6: =$BD$6/2*(1+'Inputs'!$C$24)^(4-1) -> 79.5906 | L6: =$BD$6/2*(1+'Inputs'!$C$24)^(4-1) -> 79.5906 | M6: =$BD$6/2*(1+'Inputs'!$C$24)^(5-1) -> 81.182412 | N6: =$BD$6/2*(1+'Inputs'!$C$24)^(5-1) -> 81.182412 | O6: =$BD$6/2*(1+'Inputs'!$C$24)^(6-1) -> 82.80606 | P6: =$BD$6/2*(1+'Inputs'!$C$24)^(6-1) -> 82.80606 | Q6: =$BD$6/2*(1+'Inputs'!$C$24)^(7-1) -> 84.462181 | R6: =$BD$6/2*(1+'Inputs'!$C$24)^(7-1) -> 84.462181 | S6: =$BD$6/2*(1+'Inputs'!$C$24)^(8-1) -> 86.151425 | T6: =$BD$6/2*(1+'Inputs'!$C$24)^(8-1) -> 86.151425 | U6: =$BD$6/2*(1+'Inputs'!$C$24)^(9-1) -> 87.874454 | V6: =$BD$6/2*(1+'Inputs'!$C$24)^(9-1) -> 87.874454 | W6: =$BD$6/2*(1+'Inputs'!$C$24)^(10-1) -> 89.631943 | X6: =$BD$6/2*(1+'Inputs'!$C$24)^(10-1) -> 89.631943 | Y6: =$BD$6/2*(1+'Inputs'!$C$24)^(11-1) -> 91.424581 | Z6: =$BD$6/2*(1+'Inputs'!$C$24)^(11-1) -> 91.424581 | AA6: =$BD$6/2*(1+'Inputs'!$C$24)^(12-1) -> 93.253073 | AB6: =$BD$6/2*(1+'Inputs'!$C$24)^(12-1) -> 93.253073 | AC6: =$BD$6/2*(1+'Inputs'!$C$24)^(13-1) -> 95.118135 | AD6: =$BD$6/2*(1+'Inputs'!$C$24)^(13-1) -> 95.118135 | AE6: =$BD$6/2*(1+'Inputs'!$C$24)^(14-1) -> 97.020497 | AF6: =$BD$6/2*(1+'Inputs'!$C$24)^(14-1) -> 97.020497 | AG6: =$BD$6/2*(1+'Inputs'!$C$24)^(15-1) -> 98.960907 | AH6: =$BD$6/2*(1+'Inputs'!$C$24)^(15-1) -> 98.960907 | AI6: =$BD$6/2*(1+'Inputs'!$C$24)^(16-1) -> 100.94013 | AJ6: =$BD$6/2*(1+'Inputs'!$C$24)^(16-1) -> 100.94013 | AK6: =$BD$6/2*(1+'Inputs'!$C$24)^(17-1) -> 102.95893 | AL6: =$BD$6/2*(1+'Inputs'!$C$24)^(17-1) -> 102.95893 | AM6: =$BD$6/2*(1+'Inputs'!$C$24)^(18-1) -> 105.01811 | AN6: =$BD$6/2*(1+'Inputs'!$C$24)^(18-1) -> 105.01811 | AO6: =$BD$6/2*(1+'Inputs'!$C$24)^(19-1) -> 107.11847 | AP6: =$BD$6/2*(1+'Inputs'!$C$24)^(19-1) -> 107.11847 | AQ6: =$BD$6/2*(1+'Inputs'!$C$24)^(20-1) -> 109.26084 | AR6: =$BD$6/2*(1+'Inputs'!$C$24)^(20-1) -> 109.26084 | AS6: =$BD$6/2*(1+'Inputs'!$C$24)^(21-1) -> 111.44605 | AT6: =$BD$6/2*(1+'Inputs'!$C$24)^(21-1) -> 111.44605 | AU6: =$BD$6/2*(1+'Inputs'!$C$24)^(22-1) -> 113.67498 | AV6: =$BD$6/2*(1+'Inputs'!$C$24)^(22-1) -> 113.67498 | AW6: =$BD$6/2*(1+'Inputs'!$C$24)^(23-1) -> 115.94848 | AX6: =$BD$6/2*(1+'Inputs'!$C$24)^(23-1) -> 115.94848 | AY6: =$BD$6/2*(1+'Inputs'!$C$24)^(24-1) -> 118.26744 | AZ6: =$BD$6/2*(1+'Inputs'!$C$24)^(24-1) -> 118.26744 | BA6: =$BD$6/2*(1+'Inputs'!$C$24)^(25-1) -> 120.63279 | BB6: =$BD$6/2*(1+'Inputs'!$C$24)^(25-1) -> 120.63279 | BD6: 150
A7: Insurance | B7: kEUR | C7: 0 | D7: 0 | E7: =$BD$7/2*(1+'Inputs'!$C$24)^(1-1) -> 50 | F7: =$BD$7/2*(1+'Inputs'!$C$24)^(1-1) -> 50 | G7: =$BD$7/2*(1+'Inputs'!$C$24)^(2-1) -> 51 | H7: =$BD$7/2*(1+'Inputs'!$C$24)^(2-1) -> 51 | I7: =$BD$7/2*(1+'Inputs'!$C$24)^(3-1) -> 52.02 | J7: =$BD$7/2*(1+'Inputs'!$C$24)^(3-1) -> 52.02 | K7: =$BD$7/2*(1+'Inputs'!$C$24)^(4-1) -> 53.0604 | L7: =$BD$7/2*(1+'Inputs'!$C$24)^(4-1) -> 53.0604 | M7: =$BD$7/2*(1+'Inputs'!$C$24)^(5-1) -> 54.121608 | N7: =$BD$7/2*(1+'Inputs'!$C$24)^(5-1) -> 54.121608 | O7: =$BD$7/2*(1+'Inputs'!$C$24)^(6-1) -> 55.20404 | P7: =$BD$7/2*(1+'Inputs'!$C$24)^(6-1) -> 55.20404 | Q7: =$BD$7/2*(1+'Inputs'!$C$24)^(7-1) -> 56.308121 | R7: =$BD$7/2*(1+'Inputs'!$C$24)^(7-1) -> 56.308121 | S7: =$BD$7/2*(1+'Inputs'!$C$24)^(8-1) -> 57.434283 | T7: =$BD$7/2*(1+'Inputs'!$C$24)^(8-1) -> 57.434283 | U7: =$BD$7/2*(1+'Inputs'!$C$24)^(9-1) -> 58.582969 | V7: =$BD$7/2*(1+'Inputs'!$C$24)^(9-1) -> 58.582969 | W7: =$BD$7/2*(1+'Inputs'!$C$24)^(10-1) -> 59.754628 | X7: =$BD$7/2*(1+'Inputs'!$C$24)^(10-1) -> 59.754628 | Y7: =$BD$7/2*(1+'Inputs'!$C$24)^(11-1) -> 60.949721 | Z7: =$BD$7/2*(1+'Inputs'!$C$24)^(11-1) -> 60.949721 | AA7: =$BD$7/2*(1+'Inputs'!$C$24)^(12-1) -> 62.168715 | AB7: =$BD$7/2*(1+'Inputs'!$C$24)^(12-1) -> 62.168715 | AC7: =$BD$7/2*(1+'Inputs'!$C$24)^(13-1) -> 63.41209 | AD7: =$BD$7/2*(1+'Inputs'!$C$24)^(13-1) -> 63.41209 | AE7: =$BD$7/2*(1+'Inputs'!$C$24)^(14-1) -> 64.680332 | AF7: =$BD$7/2*(1+'Inputs'!$C$24)^(14-1) -> 64.680332 | AG7: =$BD$7/2*(1+'Inputs'!$C$24)^(15-1) -> 65.973938 | AH7: =$BD$7/2*(1+'Inputs'!$C$24)^(15-1) -> 65.973938 | AI7: =$BD$7/2*(1+'Inputs'!$C$24)^(16-1) -> 67.293417 | AJ7: =$BD$7/2*(1+'Inputs'!$C$24)^(16-1) -> 67.293417 | AK7: =$BD$7/2*(1+'Inputs'!$C$24)^(17-1) -> 68.639285 | AL7: =$BD$7/2*(1+'Inputs'!$C$24)^(17-1) -> 68.639285 | AM7: =$BD$7/2*(1+'Inputs'!$C$24)^(18-1) -> 70.012071 | AN7: =$BD$7/2*(1+'Inputs'!$C$24)^(18-1) -> 70.012071 | AO7: =$BD$7/2*(1+'Inputs'!$C$24)^(19-1) -> 71.412312 | AP7: =$BD$7/2*(1+'Inputs'!$C$24)^(19-1) -> 71.412312 | AQ7: =$BD$7/2*(1+'Inputs'!$C$24)^(20-1) -> 72.840559 | AR7: =$BD$7/2*(1+'Inputs'!$C$24)^(20-1) -> 72.840559 | AS7: =$BD$7/2*(1+'Inputs'!$C$24)^(21-1) -> 74.29737 | AT7: =$BD$7/2*(1+'Inputs'!$C$24)^(21-1) -> 74.29737 | AU7: =$BD$7/2*(1+'Inputs'!$C$24)^(22-1) -> 75.783317 | AV7: =$BD$7/2*(1+'Inputs'!$C$24)^(22-1) -> 75.783317 | AW7: =$BD$7/2*(1+'Inputs'!$C$24)^(23-1) -> 77.298984 | AX7: =$BD$7/2*(1+'Inputs'!$C$24)^(23-1) -> 77.298984 | AY7: =$BD$7/2*(1+'Inputs'!$C$24)^(24-1) -> 78.844963 | AZ7: =$BD$7/2*(1+'Inputs'!$C$24)^(24-1) -> 78.844963 | BA7: =$BD$7/2*(1+'Inputs'!$C$24)^(25-1) -> 80.421862 | BB7: =$BD$7/2*(1+'Inputs'!$C$24)^(25-1) -> 80.421862 | BD7: 100
A8: Maintenance | B8: kEUR | C8: 0 | D8: 0 | E8: =$BD$8/2*(1+'Inputs'!$C$24)^(1-1) -> 40 | F8: =$BD$8/2*(1+'Inputs'!$C$24)^(1-1) -> 40 | G8: =$BD$8/2*(1+'Inputs'!$C$24)^(2-1) -> 40.8 | H8: =$BD$8/2*(1+'Inputs'!$C$24)^(2-1) -> 40.8 | I8: =$BD$8/2*(1+'Inputs'!$C$24)^(3-1) -> 41.616 | J8: =$BD$8/2*(1+'Inputs'!$C$24)^(3-1) -> 41.616 | K8: =$BD$8/2*(1+'Inputs'!$C$24)^(4-1) -> 42.44832 | L8: =$BD$8/2*(1+'Inputs'!$C$24)^(4-1) -> 42.44832 | M8: =$BD$8/2*(1+'Inputs'!$C$24)^(5-1) -> 43.297286 | N8: =$BD$8/2*(1+'Inputs'!$C$24)^(5-1) -> 43.297286 | O8: =$BD$8/2*(1+'Inputs'!$C$24)^(6-1) -> 44.163232 | P8: =$BD$8/2*(1+'Inputs'!$C$24)^(6-1) -> 44.163232 | Q8: =$BD$8/2*(1+'Inputs'!$C$24)^(7-1) -> 45.046497 | R8: =$BD$8/2*(1+'Inputs'!$C$24)^(7-1) -> 45.046497 | S8: =$BD$8/2*(1+'Inputs'!$C$24)^(8-1) -> 45.947427 | T8: =$BD$8/2*(1+'Inputs'!$C$24)^(8-1) -> 45.947427 | U8: =$BD$8/2*(1+'Inputs'!$C$24)^(9-1) -> 46.866375 | V8: =$BD$8/2*(1+'Inputs'!$C$24)^(9-1) -> 46.866375 | W8: =$BD$8/2*(1+'Inputs'!$C$24)^(10-1) -> 47.803703 | X8: =$BD$8/2*(1+'Inputs'!$C$24)^(10-1) -> 47.803703 | Y8: =$BD$8/2*(1+'Inputs'!$C$24)^(11-1) -> 48.759777 | Z8: =$BD$8/2*(1+'Inputs'!$C$24)^(11-1) -> 48.759777 | AA8: =$BD$8/2*(1+'Inputs'!$C$24)^(12-1) -> 49.734972 | AB8: =$BD$8/2*(1+'Inputs'!$C$24)^(12-1) -> 49.734972 | AC8: =$BD$8/2*(1+'Inputs'!$C$24)^(13-1) -> 50.729672 | AD8: =$BD$8/2*(1+'Inputs'!$C$24)^(13-1) -> 50.729672 | AE8: =$BD$8/2*(1+'Inputs'!$C$24)^(14-1) -> 51.744265 | AF8: =$BD$8/2*(1+'Inputs'!$C$24)^(14-1) -> 51.744265 | AG8: =$BD$8/2*(1+'Inputs'!$C$24)^(15-1) -> 52.779151 | AH8: =$BD$8/2*(1+'Inputs'!$C$24)^(15-1) -> 52.779151 | AI8: =$BD$8/2*(1+'Inputs'!$C$24)^(16-1) -> 53.834734 | AJ8: =$BD$8/2*(1+'Inputs'!$C$24)^(16-1) -> 53.834734 | AK8: =$BD$8/2*(1+'Inputs'!$C$24)^(17-1) -> 54.911428 | AL8: =$BD$8/2*(1+'Inputs'!$C$24)^(17-1) -> 54.911428 | AM8: =$BD$8/2*(1+'Inputs'!$C$24)^(18-1) -> 56.009657 | AN8: =$BD$8/2*(1+'Inputs'!$C$24)^(18-1) -> 56.009657 | AO8: =$BD$8/2*(1+'Inputs'!$C$24)^(19-1) -> 57.12985 | AP8: =$BD$8/2*(1+'Inputs'!$C$24)^(19-1) -> 57.12985 | AQ8: =$BD$8/2*(1+'Inputs'!$C$24)^(20-1) -> 58.272447 | AR8: =$BD$8/2*(1+'Inputs'!$C$24)^(20-1) -> 58.272447 | AS8: =$BD$8/2*(1+'Inputs'!$C$24)^(21-1) -> 59.437896 | AT8: =$BD$8/2*(1+'Inputs'!$C$24)^(21-1) -> 59.437896 | AU8: =$BD$8/2*(1+'Inputs'!$C$24)^(22-1) -> 60.626654 | AV8: =$BD$8/2*(1+'Inputs'!$C$24)^(22-1) -> 60.626654 | AW8: =$BD$8/2*(1+'Inputs'!$C$24)^(23-1) -> 61.839187 | AX8: =$BD$8/2*(1+'Inputs'!$C$24)^(23-1) -> 61.839187 | AY8: =$BD$8/2*(1+'Inputs'!$C$24)^(24-1) -> 63.075971 | AZ8: =$BD$8/2*(1+'Inputs'!$C$24)^(24-1) -> 63.075971 | BA8: =$BD$8/2*(1+'Inputs'!$C$24)^(25-1) -> 64.33749 | BB8: =$BD$8/2*(1+'Inputs'!$C$24)^(25-1) -> 64.33749 | BD8: 80
A9: Lease & Tax | B9: kEUR | C9: 0 | D9: 0 | E9: =$BD$9/2*(1+'Inputs'!$C$24)^(1-1) -> 25 | F9: =$BD$9/2*(1+'Inputs'!$C$24)^(1-1) -> 25 | G9: =$BD$9/2*(1+'Inputs'!$C$24)^(2-1) -> 25.5 | H9: =$BD$9/2*(1+'Inputs'!$C$24)^(2-1) -> 25.5 | I9: =$BD$9/2*(1+'Inputs'!$C$24)^(3-1) -> 26.01 | J9: =$BD$9/2*(1+'Inputs'!$C$24)^(3-1) -> 26.01 | K9: =$BD$9/2*(1+'Inputs'!$C$24)^(4-1) -> 26.5302 | L9: =$BD$9/2*(1+'Inputs'!$C$24)^(4-1) -> 26.5302 | M9: =$BD$9/2*(1+'Inputs'!$C$24)^(5-1) -> 27.060804 | N9: =$BD$9/2*(1+'Inputs'!$C$24)^(5-1) -> 27.060804 | O9: =$BD$9/2*(1+'Inputs'!$C$24)^(6-1) -> 27.60202 | P9: =$BD$9/2*(1+'Inputs'!$C$24)^(6-1) -> 27.60202 | Q9: =$BD$9/2*(1+'Inputs'!$C$24)^(7-1) -> 28.15406 | R9: =$BD$9/2*(1+'Inputs'!$C$24)^(7-1) -> 28.15406 | S9: =$BD$9/2*(1+'Inputs'!$C$24)^(8-1) -> 28.717142 | T9: =$BD$9/2*(1+'Inputs'!$C$24)^(8-1) -> 28.717142 | U9: =$BD$9/2*(1+'Inputs'!$C$24)^(9-1) -> 29.291485 | V9: =$BD$9/2*(1+'Inputs'!$C$24)^(9-1) -> 29.291485 | W9: =$BD$9/2*(1+'Inputs'!$C$24)^(10-1) -> 29.877314 | X9: =$BD$9/2*(1+'Inputs'!$C$24)^(10-1) -> 29.877314 | Y9: =$BD$9/2*(1+'Inputs'!$C$24)^(11-1) -> 30.47486 | Z9: =$BD$9/2*(1+'Inputs'!$C$24)^(11-1) -> 30.47486 | AA9: =$BD$9/2*(1+'Inputs'!$C$24)^(12-1) -> 31.084358 | AB9: =$BD$9/2*(1+'Inputs'!$C$24)^(12-1) -> 31.084358 | AC9: =$BD$9/2*(1+'Inputs'!$C$24)^(13-1) -> 31.706045 | AD9: =$BD$9/2*(1+'Inputs'!$C$24)^(13-1) -> 31.706045 | AE9: =$BD$9/2*(1+'Inputs'!$C$24)^(14-1) -> 32.340166 | AF9: =$BD$9/2*(1+'Inputs'!$C$24)^(14-1) -> 32.340166 | AG9: =$BD$9/2*(1+'Inputs'!$C$24)^(15-1) -> 32.986969 | AH9: =$BD$9/2*(1+'Inputs'!$C$24)^(15-1) -> 32.986969 | AI9: =$BD$9/2*(1+'Inputs'!$C$24)^(16-1) -> 33.646708 | AJ9: =$BD$9/2*(1+'Inputs'!$C$24)^(16-1) -> 33.646708 | AK9: =$BD$9/2*(1+'Inputs'!$C$24)^(17-1) -> 34.319643 | AL9: =$BD$9/2*(1+'Inputs'!$C$24)^(17-1) -> 34.319643 | AM9: =$BD$9/2*(1+'Inputs'!$C$24)^(18-1) -> 35.006035 | AN9: =$BD$9/2*(1+'Inputs'!$C$24)^(18-1) -> 35.006035 | AO9: =$BD$9/2*(1+'Inputs'!$C$24)^(19-1) -> 35.706156 | AP9: =$BD$9/2*(1+'Inputs'!$C$24)^(19-1) -> 35.706156 | AQ9: =$BD$9/2*(1+'Inputs'!$C$24)^(20-1) -> 36.420279 | AR9: =$BD$9/2*(1+'Inputs'!$C$24)^(20-1) -> 36.420279 | AS9: =$BD$9/2*(1+'Inputs'!$C$24)^(21-1) -> 37.148685 | AT9: =$BD$9/2*(1+'Inputs'!$C$24)^(21-1) -> 37.148685 | AU9: =$BD$9/2*(1+'Inputs'!$C$24)^(22-1) -> 37.891659 | AV9: =$BD$9/2*(1+'Inputs'!$C$24)^(22-1) -> 37.891659 | AW9: =$BD$9/2*(1+'Inputs'!$C$24)^(23-1) -> 38.649492 | AX9: =$BD$9/2*(1+'Inputs'!$C$24)^(23-1) -> 38.649492 | AY9: =$BD$9/2*(1+'Inputs'!$C$24)^(24-1) -> 39.422482 | AZ9: =$BD$9/2*(1+'Inputs'!$C$24)^(24-1) -> 39.422482 | BA9: =$BD$9/2*(1+'Inputs'!$C$24)^(25-1) -> 40.210931 | BB9: =$BD$9/2*(1+'Inputs'!$C$24)^(25-1) -> 40.210931 | BD9: 50
A10: Total OpEx | C10: =SUM(C6:C9) -> 0 | D10: =SUM(D6:D9) -> 0 | E10: =SUM(E6:E9) -> 190 | F10: =SUM(F6:F9) -> 190 | G10: =SUM(G6:G9) -> 193.8 | H10: =SUM(H6:H9) -> 193.8 | I10: =SUM(I6:I9) -> 197.676 | J10: =SUM(J6:J9) -> 197.676 | ... BB10: =SUM(BB6:BB9) -> 305.60308
A12: TOTAL OPEX (kEUR, life of project) | C12: =SUM(C10:BB10) -> 12171.514

Sheet Revenue
A1: Generic Solar PV — Revenue
A3: Period | C3: P1 | D3: P2 | E3: P3 | F3: P4 | G3: P5 | H3: P6 | I3: P7 | J3: P8 | K3: P9 | L3: P10 | M3: P11 | N3: P12 | O3: P13 | P3: P14 | Q3: P15 | R3: P16 | S3: P17 | T3: P18 | U3: P19 | V3: P20 | W3: P21 | X3: P22 | Y3: P23 | Z3: P24 | AA3: P25 | AB3: P26 | AC3: P27 | AD3: P28 | AE3: P29 | AF3: P30 | AG3: P31 | AH3: P32 | AI3: P33 | AJ3: P34 | AK3: P35 | AL3: P36 | AM3: P37 | AN3: P38 | AO3: P39 | AP3: P40 | AQ3: P41 | AR3: P42 | AS3: P43 | AT3: P44 | AU3: P45 | AV3: P46 | AW3: P47 | AX3: P48 | AY3: P49 | AZ3: P50 | BA3: P51 | BB3: P52
A4: Operating year | C4: - | D4: - | E4: 1 | F4: 1 | G4: 2 | H4: 2 | I4: 3 | J4: 3 | K4: 4 | L4: 4 | M4: 5 | N4: 5 | O4: 6 | P4: 6 | Q4: 7 | R4: 7 | S4: 8 | T4: 8 | U4: 9 | V4: 9 | W4: 10 | X4: 10 | Y4: 11 | Z4: 11 | AA4: 12 | AB4: 12 | AC4: 13 | AD4: 13 | AE4: 14 | AF4: 14 | AG4: 15 | AH4: 15 | AI4: 16 | AJ4: 16 | AK4: 17 | AL4: 17 | AM4: 18 | AN4: 18 | AO4: 19 | AP4: 19 | AQ4: 20 | AR4: 20 | AS4: 21 | AT4: 21 | AU4: 22 | AV4: 22 | AW4: 23 | AX4: 23 | AY4: 24 | AZ4: 24 | BA4: 25 | BB4: 25
A6: Generation (MWh) | C6: 0 | D6: 0 | E6: ='Inputs'!$C$11*'Inputs'!$C$12/2*'Inputs'!$C$14*(1-'Inputs'!$C$13)^(1-1) -> 36753.75 | F6: ='Inputs'!$C$11*'Inputs'!$C$12/2*'Inputs'!$C$14*(1-'Inputs'!$C$13)^(1-1) -> 36753.75 | G6: ='Inputs'!$C$11*'Inputs'!$C$12/2*'Inputs'!$C$14*(1-'Inputs'!$C$13)^(2-1) -> 36606.735 | H6: ='Inputs'!$C$11*'Inputs'!$C$12/2*'Inputs'!$C$14*(1-'Inputs'!$C$13)^(2-1) -> 36606.735 | I6: ='Inputs'!$C$11*'Inputs'!$C$12/2*'Inputs'!$C$14*(1-'Inputs'!$C$13)^(3-1) -> 36460.308 | J6: ='Inputs'!$C$11*'Inputs'!$C$12/2*'Inputs'!$C$14*(1-'Inputs'!$C$13)^(3-1) -> 36460.308 | K6: ='Inputs'!$C$11*'Inputs'!$C$12/2*'Inputs'!$C$14*(1-'Inputs'!$C$13)^(4-1) -> 36314.467 | L6: ='Inputs'!$C$11*'Inputs'!$C$12/2*'Inputs'!$C$14*(1-'Inputs'!$C$13)^(4-1) -> 36314.467 | M6: ='Inputs'!$C$11*'Inputs'!$C$12/2*'Inputs'!$C$14*(1-'Inputs'!$C$13)^(5-1) -> 36169.209 | N6: ='Inputs'!$C$11*'Inputs'!$C$12/2*'Inputs'!$C$14*(1-'Inputs'!$C$13)^(5-1) -> 36169.209 | O6: ='Inputs'!$C$11*'Inputs'!$C$12/2*'Inputs'!$C$14*(1-'Inputs'!$C$13)^(6-1) -> 36024.532 | P6: ='Inputs'!$C$11*'Inputs'!$C$12/2*'Inputs'!$C$14*(1-'Inputs'!$C$13)^(6-1) -> 36024.532 | Q6: ='Inputs'!$C$11*'Inputs'!$C$12/2*'Inputs'!$C$14*(1-'Inputs'!$C$13)^(7-1) -> 35880.434 | R6: ='Inputs'!$C$11*'Inputs'!$C$12/2*'Inputs'!$C$14*(1-'Inputs'!$C$13)^(7-1) -> 35880.434 | S6: ='Inputs'!$C$11*'Inputs'!$C$12/2*'Inputs'!$C$14*(1-'Inputs'!$C$13)^(8-1) -> 35736.912 | T6: ='Inputs'!$C$11*'Inputs'!$C$12/2*'Inputs'!$C$14*(1-'Inputs'!$C$13)^(8-1) -> 35736.912 | U6: ='Inputs'!$C$11*'Inputs'!$C$12/2*'Inputs'!$C$14*(1-'Inputs'!$C$13)^(9-1) -> 35593.965 | V6: ='Inputs'!$C$11*'Inputs'!$C$12/2*'Inputs'!$C$14*(1-'Inputs'!$C$13)^(9-1) -> 35593.965 | W6: ='Inputs'!$C$11*'Inputs'!$C$12/2*'Inputs'!$C$14*(1-'Inputs'!$C$13)^(10-1) -> 35451.589 | X6: ='Inputs'!$C$11*'Inputs'!$C$12/2*'Inputs'!$C$14*(1-'Inputs'!$C$13)^(10-1) -> 35451.589 | Y6: ='Inputs'!$C$11*'Inputs'!$C$12/2*'Inputs'!$C$14*(1-'Inputs'!$C$13)^(11-1) -> 35309.782 | Z6: ='Inputs'!$C$11*'Inputs'!$C$12/2*'Inputs'!$C$14*(1-'Inputs'!$C$13)^(11-1) -> 35309.782 | AA6: ='Inputs'!$C$11*'Inputs'!$C$12/2*'Inputs'!$C$14*(1-'Inputs'!$C$13)^(12-1) -> 35168.543 | AB6: ='Inputs'!$C$11*'Inputs'!$C$12/2*'Inputs'!$C$14*(1-'Inputs'!$C$13)^(12-1) -> 35168.543 | AC6: ='Inputs'!$C$11*'Inputs'!$C$12/2*'Inputs'!$C$14*(1-'Inputs'!$C$13)^(13-1) -> 35027.869 | AD6: ='Inputs'!$C$11*'Inputs'!$C$12/2*'Inputs'!$C$14*(1-'Inputs'!$C$13)^(13-1) -> 35027.869 | AE6: ='Inputs'!$C$11*'Inputs'!$C$12/2*'Inputs'!$C$14*(1-'Inputs'!$C$13)^(14-1) -> 34887.758 | AF6: ='Inputs'!$C$11*'Inputs'!$C$12/2*'Inputs'!$C$14*(1-'Inputs'!$C$13)^(14-1) -> 34887.758 | AG6: ='Inputs'!$C$11*'Inputs'!$C$12/2*'Inputs'!$C$14*(1-'Inputs'!$C$13)^(15-1) -> 34748.207 | AH6: ='Inputs'!$C$11*'Inputs'!$C$12/2*'Inputs'!$C$14*(1-'Inputs'!$C$13)^(15-1) -> 34748.207 | AI6: ='Inputs'!$C$11*'Inputs'!$C$12/2*'Inputs'!$C$14*(1-'Inputs'!$C$13)^(16-1) -> 34609.214 | AJ6: ='Inputs'!$C$11*'Inputs'!$C$12/2*'Inputs'!$C$14*(1-'Inputs'!$C$13)^(16-1) -> 34609.214 | AK6: ='Inputs'!$C$11*'Inputs'!$C$12/2*'Inputs'!$C$14*(1-'Inputs'!$C$13)^(17-1) -> 34470.777 | AL6: ='Inputs'!$C$11*'Inputs'!$C$12/2*'Inputs'!$C$14*(1-'Inputs'!$C$13)^(17-1) -> 34470.777 | AM6: ='Inputs'!$C$11*'Inputs'!$C$12/2*'Inputs'!$C$14*(1-'Inputs'!$C$13)^(18-1) -> 34332.894 | AN6: ='Inputs'!$C$11*'Inputs'!$C$12/2*'Inputs'!$C$14*(1-'Inputs'!$C$13)^(18-1) -> 34332.894 | AO6: ='Inputs'!$C$11*'Inputs'!$C$12/2*'Inputs'!$C$14*(1-'Inputs'!$C$13)^(19-1) -> 34195.562 | AP6: ='Inputs'!$C$11*'Inputs'!$C$12/2*'Inputs'!$C$14*(1-'Inputs'!$C$13)^(19-1) -> 34195.562 | AQ6: ='Inputs'!$C$11*'Inputs'!$C$12/2*'Inputs'!$C$14*(1-'Inputs'!$C$13)^(20-1) -> 34058.78 | AR6: ='Inputs'!$C$11*'Inputs'!$C$12/2*'Inputs'!$C$14*(1-'Inputs'!$C$13)^(20-1) -> 34058.78 | AS6: ='Inputs'!$C$11*'Inputs'!$C$12/2*'Inputs'!$C$14*(1-'Inputs'!$C$13)^(21-1) -> 33922.545 | AT6: ='Inputs'!$C$11*'Inputs'!$C$12/2*'Inputs'!$C$14*(1-'Inputs'!$C$13)^(21-1) -> 33922.545 | AU6: ='Inputs'!$C$11*'Inputs'!$C$12/2*'Inputs'!$C$14*(1-'Inputs'!$C$13)^(22-1) -> 33786.855 | AV6: ='Inputs'!$C$11*'Inputs'!$C$12/2*'Inputs'!$C$14*(1-'Inputs'!$C$13)^(22-1) -> 33786.855 | AW6: ='Inputs'!$C$11*'Inputs'!$C$12/2*'Inputs'!$C$14*(1-'Inputs'!$C$13)^(23-1) -> 33651.707 | AX6: ='Inputs'!$C$11*'Inputs'!$C$12/2*'Inputs'!$C$14*(1-'Inputs'!$C$13)^(23-1) -> 33651.707 | AY6: ='Inputs'!$C$11*'Inputs'!$C$12/2*'Inputs'!$C$14*(1-'Inputs'!$C$13)^(24-1) -> 33517.1 | AZ6: ='Inputs'!$C$11*'Inputs'!$C$12/2*'Inputs'!$C$14*(1-'Inputs'!$C$13)^(24-1) -> 33517.1 | BA6: ='Inputs'!$C$11*'Inputs'!$C$12/2*'Inputs'!$C$14*(1-'Inputs'!$C$13)^(25-1) -> 33383.032 | BB6: ='Inputs'!$C$11*'Inputs'!$C$12/2*'Inputs'!$C$14*(1-'Inputs'!$C$13)^(25-1) -> 33383.032
A7: PPA tariff this year (EUR/MWh) | C7: 0 | D7: 0 | E7: ='Inputs'!$C$15*(1+'Inputs'!$C$17)^(1-1) -> 55 | F7: ='Inputs'!$C$15*(1+'Inputs'!$C$17)^(1-1) -> 55 | G7: ='Inputs'!$C$15*(1+'Inputs'!$C$17)^(2-1) -> 56.1 | H7: ='Inputs'!$C$15*(1+'Inputs'!$C$17)^(2-1) -> 56.1 | I7: ='Inputs'!$C$15*(1+'Inputs'!$C$17)^(3-1) -> 57.222 | J7: ='Inputs'!$C$15*(1+'Inputs'!$C$17)^(3-1) -> 57.222 | K7: ='Inputs'!$C$15*(1+'Inputs'!$C$17)^(4-1) -> 58.36644 | L7: ='Inputs'!$C$15*(1+'Inputs'!$C$17)^(4-1) -> 58.36644 | M7: ='Inputs'!$C$15*(1+'Inputs'!$C$17)^(5-1) -> 59.533769 | N7: ='Inputs'!$C$15*(1+'Inputs'!$C$17)^(5-1) -> 59.533769 | O7: ='Inputs'!$C$15*(1+'Inputs'!$C$17)^(6-1) -> 60.724444 | P7: ='Inputs'!$C$15*(1+'Inputs'!$C$17)^(6-1) -> 60.724444 | Q7: ='Inputs'!$C$15*(1+'Inputs'!$C$17)^(7-1) -> 61.938933 | R7: ='Inputs'!$C$15*(1+'Inputs'!$C$17)^(7-1) -> 61.938933 | S7: ='Inputs'!$C$15*(1+'Inputs'!$C$17)^(8-1) -> 63.177712 | T7: ='Inputs'!$C$15*(1+'Inputs'!$C$17)^(8-1) -> 63.177712 | U7: ='Inputs'!$C$15*(1+'Inputs'!$C$17)^(9-1) -> 64.441266 | V7: ='Inputs'!$C$15*(1+'Inputs'!$C$17)^(9-1) -> 64.441266 | W7: ='Inputs'!$C$15*(1+'Inputs'!$C$17)^(10-1) -> 65.730091 | X7: ='Inputs'!$C$15*(1+'Inputs'!$C$17)^(10-1) -> 65.730091 | Y7: ='Inputs'!$C$15*(1+'Inputs'!$C$17)^(11-1) -> 67.044693 | Z7: ='Inputs'!$C$15*(1+'Inputs'!$C$17)^(11-1) -> 67.044693 | AA7: ='Inputs'!$C$15*(1+'Inputs'!$C$17)^(12-1) -> 68.385587 | AB7: ='Inputs'!$C$15*(1+'Inputs'!$C$17)^(12-1) -> 68.385587 | AC7: ='Inputs'!$C$15*(1+'Inputs'!$C$17)^(13-1) -> 69.753299 | AD7: ='Inputs'!$C$15*(1+'Inputs'!$C$17)^(13-1) -> 69.753299 | AE7: ='Inputs'!$C$15*(1+'Inputs'!$C$17)^(14-1) -> 71.148365 | AF7: ='Inputs'!$C$15*(1+'Inputs'!$C$17)^(14-1) -> 71.148365 | AG7: ='Inputs'!$C$15*(1+'Inputs'!$C$17)^(15-1) -> 72.571332 | AH7: ='Inputs'!$C$15*(1+'Inputs'!$C$17)^(15-1) -> 72.571332 | AI7: ='Inputs'!$C$15*(1+'Inputs'!$C$17)^(16-1) -> 74.022759 | AJ7: ='Inputs'!$C$15*(1+'Inputs'!$C$17)^(16-1) -> 74.022759 | AK7: ='Inputs'!$C$15*(1+'Inputs'!$C$17)^(17-1) -> 75.503214 | AL7: ='Inputs'!$C$15*(1+'Inputs'!$C$17)^(17-1) -> 75.503214 | AM7: ='Inputs'!$C$15*(1+'Inputs'!$C$17)^(18-1) -> 77.013278 | AN7: ='Inputs'!$C$15*(1+'Inputs'!$C$17)^(18-1) -> 77.013278 | AO7: ='Inputs'!$C$15*(1+'Inputs'!$C$17)^(19-1) -> 78.553544 | AP7: ='Inputs'!$C$15*(1+'Inputs'!$C$17)^(19-1) -> 78.553544 | AQ7: ='Inputs'!$C$15*(1+'Inputs'!$C$17)^(20-1) -> 80.124614 | AR7: ='Inputs'!$C$15*(1+'Inputs'!$C$17)^(20-1) -> 80.124614 | AS7: ='Inputs'!$C$15*(1+'Inputs'!$C$17)^(21-1) -> 81.727107 | AT7: ='Inputs'!$C$15*(1+'Inputs'!$C$17)^(21-1) -> 81.727107 | AU7: ='Inputs'!$C$15*(1+'Inputs'!$C$17)^(22-1) -> 83.361649 | AV7: ='Inputs'!$C$15*(1+'Inputs'!$C$17)^(22-1) -> 83.361649 | AW7: ='Inputs'!$C$15*(1+'Inputs'!$C$17)^(23-1) -> 85.028882 | AX7: ='Inputs'!$C$15*(1+'Inputs'!$C$17)^(23-1) -> 85.028882 | AY7: ='Inputs'!$C$15*(1+'Inputs'!$C$17)^(24-1) -> 86.72946 | AZ7: ='Inputs'!$C$15*(1+'Inputs'!$C$17)^(24-1) -> 86.72946 | BA7: ='Inputs'!$C$15*(1+'Inputs'!$C$17)^(25-1) -> 88.464049 | BB7: ='Inputs'!$C$15*(1+'Inputs'!$C$17)^(25-1) -> 88.464049
A8: Market price this year (EUR/MWh) | C8: 0 | D8: 0 | E8: ='Inputs'!$C$18 -> 60 | F8: ='Inputs'!$C$18 -> 60 | G8: ='Inputs'!$C$19 -> 61 | H8: ='Inputs'!$C$19 -> 61 | I8: ='Inputs'!$C$19*(1+'Inputs'!$C$20)^(3-2) -> 62.22 | J8: ='Inputs'!$C$19*(1+'Inputs'!$C$20)^(3-2) -> 62.22 | K8: ='Inputs'!$C$19*(1+'Inputs'!$C$20)^(4-2) -> 63.4644 | L8: ='Inputs'!$C$19*(1+'Inputs'!$C$20)^(4-2) -> 63.4644 | M8: ='Inputs'!$C$19*(1+'Inputs'!$C$20)^(5-2) -> 64.733688 | N8: ='Inputs'!$C$19*(1+'Inputs'!$C$20)^(5-2) -> 64.733688 | O8: ='Inputs'!$C$19*(1+'Inputs'!$C$20)^(6-2) -> 66.028362 | P8: ='Inputs'!$C$19*(1+'Inputs'!$C$20)^(6-2) -> 66.028362 | Q8: ='Inputs'!$C$19*(1+'Inputs'!$C$20)^(7-2) -> 67.348929 | R8: ='Inputs'!$C$19*(1+'Inputs'!$C$20)^(7-2) -> 67.348929 | S8: ='Inputs'!$C$19*(1+'Inputs'!$C$20)^(8-2) -> 68.695908 | T8: ='Inputs'!$C$19*(1+'Inputs'!$C$20)^(8-2) -> 68.695908 | U8: ='Inputs'!$C$19*(1+'Inputs'!$C$20)^(9-2) -> 70.069826 | V8: ='Inputs'!$C$19*(1+'Inputs'!$C$20)^(9-2) -> 70.069826 | W8: ='Inputs'!$C$19*(1+'Inputs'!$C$20)^(10-2) -> 71.471222 | X8: ='Inputs'!$C$19*(1+'Inputs'!$C$20)^(10-2) -> 71.471222 | Y8: ='Inputs'!$C$19*(1+'Inputs'!$C$20)^(11-2) -> 72.900647 | Z8: ='Inputs'!$C$19*(1+'Inputs'!$C$20)^(11-2) -> 72.900647 | AA8: ='Inputs'!$C$19*(1+'Inputs'!$C$20)^(12-2) -> 74.35866 | AB8: ='Inputs'!$C$19*(1+'Inputs'!$C$20)^(12-2) -> 74.35866 | AC8: ='Inputs'!$C$19*(1+'Inputs'!$C$20)^(13-2) -> 75.845833 | AD8: ='Inputs'!$C$19*(1+'Inputs'!$C$20)^(13-2) -> 75.845833 | AE8: ='Inputs'!$C$19*(1+'Inputs'!$C$20)^(14-2) -> 77.362749 | AF8: ='Inputs'!$C$19*(1+'Inputs'!$C$20)^(14-2) -> 77.362749 | AG8: ='Inputs'!$C$19*(1+'Inputs'!$C$20)^(15-2) -> 78.910004 | AH8: ='Inputs'!$C$19*(1+'Inputs'!$C$20)^(15-2) -> 78.910004 | AI8: ='Inputs'!$C$19*(1+'Inputs'!$C$20)^(16-2) -> 80.488205 | AJ8: ='Inputs'!$C$19*(1+'Inputs'!$C$20)^(16-2) -> 80.488205 | AK8: ='Inputs'!$C$19*(1+'Inputs'!$C$20)^(17-2) -> 82.097969 | AL8: ='Inputs'!$C$19*(1+'Inputs'!$C$20)^(17-2) -> 82.097969 | AM8: ='Inputs'!$C$19*(1+'Inputs'!$C$20)^(18-2) -> 83.739928 | AN8: ='Inputs'!$C$19*(1+'Inputs'!$C$20)^(18-2) -> 83.739928 | AO8: ='Inputs'!$C$19*(1+'Inputs'!$C$20)^(19-2) -> 85.414727 | AP8: ='Inputs'!$C$19*(1+'Inputs'!$C$20)^(19-2) -> 85.414727 | AQ8: ='Inputs'!$C$19*(1+'Inputs'!$C$20)^(20-2) -> 87.123021 | AR8: ='Inputs'!$C$19*(1+'Inputs'!$C$20)^(20-2) -> 87.123021 | AS8: ='Inputs'!$C$19*(1+'Inputs'!$C$20)^(21-2) -> 88.865482 | AT8: ='Inputs'!$C$19*(1+'Inputs'!$C$20)^(21-2) -> 88.865482 | AU8: ='Inputs'!$C$19*(1+'Inputs'!$C$20)^(22-2) -> 90.642791 | AV8: ='Inputs'!$C$19*(1+'Inputs'!$C$20)^(22-2) -> 90.642791 | AW8: ='Inputs'!$C$19*(1+'Inputs'!$C$20)^(23-2) -> 92.455647 | AX8: ='Inputs'!$C$19*(1+'Inputs'!$C$20)^(23-2) -> 92.455647 | AY8: ='Inputs'!$C$19*(1+'Inputs'!$C$20)^(24-2) -> 94.30476 | AZ8: ='Inputs'!$C$19*(1+'Inputs'!$C$20)^(24-2) -> 94.30476 | BA8: ='Inputs'!$C$19*(1+'Inputs'!$C$20)^(25-2) -> 96.190855 | BB8: ='Inputs'!$C$19*(1+'Inputs'!$C$20)^(25-2) -> 96.190855
A9: PPA active? (1/0) | C9: 0 | D9: 0 | E9: =IF(1<='Inputs'!$C$16,1,0) -> 1 | F9: =IF(1<='Inputs'!$C$16,1,0) -> 1 | G9: =IF(2<='Inputs'!$C$16,1,0) -> 1 | H9: =IF(2<='Inputs'!$C$16,1,0) -> 1 | I9: =IF(3<='Inputs'!$C$16,1,0) -> 1 | J9: =IF(3<='Inputs'!$C$16,1,0) -> 1 | K9: =IF(4<='Inputs'!$C$16,1,0) -> 1 | L9: =IF(4<='Inputs'!$C$16,1,0) -> 1 | M9: =IF(5<='Inputs'!$C$16,1,0) -> 1 | N9: =IF(5<='Inputs'!$C$16,1,0) -> 1 | O9: =IF(6<='Inputs'!$C$16,1,0) -> 1 | P9: =IF(6<='Inputs'!$C$16,1,0) -> 1 | Q9: =IF(7<='Inputs'!$C$16,1,0) -> 1 | R9: =IF(7<='Inputs'!$C$16,1,0) -> 1 | S9: =IF(8<='Inputs'!$C$16,1,0) -> 1 | T9: =IF(8<='Inputs'!$C$16,1,0) -> 1 | U9: =IF(9<='Inputs'!$C$16,1,0) -> 1 | V9: =IF(9<='Inputs'!$C$16,1,0) -> 1 | W9: =IF(10<='Inputs'!$C$16,1,0) -> 1 | X9: =IF(10<='Inputs'!$C$16,1,0) -> 1 | Y9: =IF(11<='Inputs'!$C$16,1,0) -> 0 | Z9: =IF(11<='Inputs'!$C$16,1,0) -> 0 | AA9: =IF(12<='Inputs'!$C$16,1,0) -> 0 | AB9: =IF(12<='Inputs'!$C$16,1,0) -> 0 | AC9: =IF(13<='Inputs'!$C$16,1,0) -> 0 | AD9: =IF(13<='Inputs'!$C$16,1,0) -> 0 | AE9: =IF(14<='Inputs'!$C$16,1,0) -> 0 | AF9: =IF(14<='Inputs'!$C$16,1,0) -> 0 | AG9: =IF(15<='Inputs'!$C$16,1,0) -> 0 | AH9: =IF(15<='Inputs'!$C$16,1,0) -> 0 | AI9: =IF(16<='Inputs'!$C$16,1,0) -> 0 | AJ9: =IF(16<='Inputs'!$C$16,1,0) -> 0 | AK9: =IF(17<='Inputs'!$C$16,1,0) -> 0 | AL9: =IF(17<='Inputs'!$C$16,1,0) -> 0 | AM9: =IF(18<='Inputs'!$C$16,1,0) -> 0 | AN9: =IF(18<='Inputs'!$C$16,1,0) -> 0 | AO9: =IF(19<='Inputs'!$C$16,1,0) -> 0 | AP9: =IF(19<='Inputs'!$C$16,1,0) -> 0 | AQ9: =IF(20<='Inputs'!$C$16,1,0) -> 0 | AR9: =IF(20<='Inputs'!$C$16,1,0) -> 0 | AS9: =IF(21<='Inputs'!$C$16,1,0) -> 0 | AT9: =IF(21<='Inputs'!$C$16,1,0) -> 0 | AU9: =IF(22<='Inputs'!$C$16,1,0) -> 0 | AV9: =IF(22<='Inputs'!$C$16,1,0) -> 0 | AW9: =IF(23<='Inputs'!$C$16,1,0) -> 0 | AX9: =IF(23<='Inputs'!$C$16,1,0) -> 0 | AY9: =IF(24<='Inputs'!$C$16,1,0) -> 0 | AZ9: =IF(24<='Inputs'!$C$16,1,0) -> 0 | BA9: =IF(25<='Inputs'!$C$16,1,0) -> 0 | BB9: =IF(25<='Inputs'!$C$16,1,0) -> 0
A10: Energy revenue (PPA or merchant, kEUR) | C10: =C6*IF(C9=1,C7,C8)/1000 -> 0 | D10: =D6*IF(D9=1,D7,D8)/1000 -> 0 | E10: =E6*IF(E9=1,E7,E8)/1000 -> 2021.4562 | F10: =F6*IF(F9=1,F7,F8)/1000 -> 2021.4562 | G10: =G6*IF(G9=1,G7,G8)/1000 -> 2053.6378 | H10: =H6*IF(H9=1,H7,H8)/1000 -> 2053.6378 | I10: =I6*IF(I9=1,I7,I8)/1000 -> 2086.3317 | J10: =J6*IF(J9=1,J7,J8)/1000 -> 2086.3317 | ... BB10: =BB6*IF(BB9=1,BB7,BB8)/1000 -> 3211.1424
A11: Balancing cost (kEUR) | C11: =-C6*'Inputs'!$C$21/1000 -> 0 | D11: =-D6*'Inputs'!$C$21/1000 -> 0 | E11: =-E6*'Inputs'!$C$21/1000 -> 0 | F11: =-F6*'Inputs'!$C$21/1000 -> 0 | G11: =-G6*'Inputs'!$C$21/1000 -> 0 | H11: =-H6*'Inputs'!$C$21/1000 -> 0 | I11: =-I6*'Inputs'!$C$21/1000 -> 0 | J11: =-J6*'Inputs'!$C$21/1000 -> 0 | ... BB11: =-BB6*'Inputs'!$C$21/1000 -> 0
A12: CO2 revenue (kEUR) | C12: =C6*'Inputs'!$C$23*0/1000 -> 0 | D12: =D6*'Inputs'!$C$23*0/1000 -> 0 | E12: =E6*'Inputs'!$C$23*0/1000 -> 0 | F12: =F6*'Inputs'!$C$23*0/1000 -> 0 | G12: =G6*'Inputs'!$C$23*0/1000 -> 0 | H12: =H6*'Inputs'!$C$23*0/1000 -> 0 | I12: =I6*'Inputs'!$C$23*0/1000 -> 0 | J12: =J6*'Inputs'!$C$23*0/1000 -> 0 | ... BB12: =BB6*'Inputs'!$C$23*0/1000 -> 0
A13: Total Revenue | C13: =C10+C11+C12 -> 0 | D13: =D10+D11+D12 -> 0 | E13: =E10+E11+E12 -> 2021.4562 | F13: =F10+F11+F12 -> 2021.4562 | G13: =G10+G11+G12 -> 2053.6378 | H13: =H10+H11+H12 -> 2053.6378 | I13: =I10+I11+I12 -> 2086.3317 | J13: =J10+J11+J12 -> 2086.3317 | ... BB13: =BB10+BB11+BB12 -> 3211.1424
A15: TOTAL REVENUE (kEUR, life of project) | C15: =SUM(C13:BB13) -> 129903.91

Sheet Debt Service
A1: Generic Solar PV — Debt Service (DSCR Sculpt)
A3: Sizing note: senior debt is sized off a CFADS proxy that excludes the interest tax shield (Tax_sizing = MAX(0,EBITDA-Depreciation)*tax_rate), to avoid a circular reference between interest and tax. Realized DSCR reported on the Cash Flow tab uses the true post-interest tax.
A5: Period | C5: P1 | D5: P2 | E5: P3 | F5: P4 | G5: P5 | H5: P6 | I5: P7 | J5: P8 | K5: P9 | L5: P10 | M5: P11 | N5: P12 | O5: P13 | P5: P14 | Q5: P15 | R5: P16 | S5: P17 | T5: P18 | U5: P19 | V5: P20 | W5: P21 | X5: P22 | Y5: P23 | Z5: P24 | AA5: P25 | AB5: P26 | AC5: P27 | AD5: P28 | AE5: P29 | AF5: P30 | AG5: P31 | AH5: P32 | AI5: P33 | AJ5: P34 | AK5: P35 | AL5: P36 | AM5: P37 | AN5: P38 | AO5: P39 | AP5: P40 | AQ5: P41 | AR5: P42 | AS5: P43 | AT5: P44 | AU5: P45 | AV5: P46 | AW5: P47 | AX5: P48 | AY5: P49 | AZ5: P50 | BA5: P51 | BB5: P52
A6: Operating year | C6: - | D6: - | E6: 1 | F6: 1 | G6: 2 | H6: 2 | I6: 3 | J6: 3 | K6: 4 | L6: 4 | M6: 5 | N6: 5 | O6: 6 | P6: 6 | Q6: 7 | R6: 7 | S6: 8 | T6: 8 | U6: 9 | V6: 9 | W6: 10 | X6: 10 | Y6: 11 | Z6: 11 | AA6: 12 | AB6: 12 | AC6: 13 | AD6: 13 | AE6: 14 | AF6: 14 | AG6: 15 | AH6: 15 | AI6: 16 | AJ6: 16 | AK6: 17 | AL6: 17 | AM6: 18 | AN6: 18 | AO6: 19 | AP6: 19 | AQ6: 20 | AR6: 20 | AS6: 21 | AT6: 21 | AU6: 22 | AV6: 22 | AW6: 23 | AX6: 23 | AY6: 24 | AZ6: 24 | BA6: 25 | BB6: 25
A8: EBITDA (= Revenue - OpEx) | C8: ='Revenue'!C13-'OpEx'!C10 -> 0 | D8: ='Revenue'!D13-'OpEx'!D10 -> 0 | E8: ='Revenue'!E13-'OpEx'!E10 -> 1831.4562 | F8: ='Revenue'!F13-'OpEx'!F10 -> 1831.4562 | G8: ='Revenue'!G13-'OpEx'!G10 -> 1859.8378 | H8: ='Revenue'!H13-'OpEx'!H10 -> 1859.8378 | I8: ='Revenue'!I13-'OpEx'!I10 -> 1888.6557 | J8: ='Revenue'!J13-'OpEx'!J10 -> 1888.6557 | ... BB8: ='Revenue'!BB13-'OpEx'!BB10 -> 2905.5393
A9: Depreciation (straight-line, kEUR) | C9: 0 | D9: 0 | E9: ='CapEx'!$BD$11/'Inputs'!$C$37/2 -> 825 | F9: ='CapEx'!$BD$11/'Inputs'!$C$37/2 -> 825 | G9: ='CapEx'!$BD$11/'Inputs'!$C$37/2 -> 825 | H9: ='CapEx'!$BD$11/'Inputs'!$C$37/2 -> 825 | I9: ='CapEx'!$BD$11/'Inputs'!$C$37/2 -> 825 | J9: ='CapEx'!$BD$11/'Inputs'!$C$37/2 -> 825 | K9: ='CapEx'!$BD$11/'Inputs'!$C$37/2 -> 825 | L9: ='CapEx'!$BD$11/'Inputs'!$C$37/2 -> 825 | ... AR9: ='CapEx'!$BD$11/'Inputs'!$C$37/2 -> 825 | AS9: 0 | AT9: 0 | AU9: 0 | AV9: 0 | AW9: 0 | AX9: 0 | AY9: 0 | AZ9: 0 | BA9: 0 | BB9: 0
A10: Tax (sizing proxy, no interest shield) | C10: =MAX(0,C8-C9)*'Inputs'!$C$33 -> 0 | D10: =MAX(0,D8-D9)*'Inputs'!$C$33 -> 0 | E10: =MAX(0,E8-E9)*'Inputs'!$C$33 -> 251.61406 | F10: =MAX(0,F8-F9)*'Inputs'!$C$33 -> 251.61406 | G10: =MAX(0,G8-G9)*'Inputs'!$C$33 -> 258.70946 | H10: =MAX(0,H8-H9)*'Inputs'!$C$33 -> 258.70946 | I10: =MAX(0,I8-I9)*'Inputs'!$C$33 -> 265.91394 | J10: =MAX(0,J8-J9)*'Inputs'!$C$33 -> 265.91394 | ... BB10: =MAX(0,BB8-BB9)*'Inputs'!$C$33 -> 726.38483
A11: CFADS (sizing proxy) | C11: =C8-C10 -> 0 | D11: =D8-D10 -> 0 | E11: =E8-E10 -> 1579.8422 | F11: =F8-F10 -> 1579.8422 | G11: =G8-G10 -> 1601.1284 | H11: =H8-H10 -> 1601.1284 | I11: =I8-I10 -> 1622.7418 | J11: =J8-J10 -> 1622.7418 | ... BB11: =BB8-BB10 -> 2179.1545
A13: Debt service capacity per period (CFADS_sizing/target DSCR) | C13: 0 | D13: 0 | E13: =E11/'Inputs'!$C$32 -> 1316.5352 | F13: =F11/'Inputs'!$C$32 -> 1316.5352 | G13: =G11/'Inputs'!$C$32 -> 1334.2736 | H13: =H11/'Inputs'!$C$32 -> 1334.2736 | I13: =I11/'Inputs'!$C$32 -> 1352.2848 | J13: =J11/'Inputs'!$C$32 -> 1352.2848 | K13: =K11/'Inputs'!$C$32 -> 1370.5729 | L13: =L11/'Inputs'!$C$32 -> 1370.5729 | ... AH13: =AH11/'Inputs'!$C$32 -> 1728.9251 | AI13: 0 | AJ13: 0 | AK13: 0 | AL13: 0 | AM13: 0 | AN13: 0 | AO13: 0 | AP13: 0 | AQ13: 0 | AR13: 0 | AS13: 0 | AT13: 0 | AU13: 0 | AV13: 0 | AW13: 0 | AX13: 0 | AY13: 0 | AZ13: 0 | BA13: 0 | BB13: 0
A14: Sized senior debt (NPV of debt-service capacity) | C14: =NPV(('Inputs'!$C$30+'Inputs'!$C$31/10000)/2,E13:AH13) -> 29620.915
A15: Gearing cap amount | C15: ='Inputs'!$C$28*'CapEx'!$BD$11 -> 24750
A16: SENIOR DEBT (sized, capped at gearing) | C16: =MIN(C14,C15) -> 24750
A17: Schedule rescale factor (gearing-cap senior debt / DSCR-sized debt, capped at 1) | C17: =IF(C14>0,MIN(1,C16/C14),1)
A18: Rescaled debt service capacity (capacity x rescale factor) | C18: 0 | D18: 0 | E18: =E13*$C$17 | F18: =F13*$C$17 | G18: =G13*$C$17 | H18: =H13*$C$17 | I18: =I13*$C$17 | J18: =J13*$C$17 | K18: =K13*$C$17 | L18: =L13*$C$17 | ... AH18: =AH13*$C$17 | AI18: 0 | AJ18: 0 | AK18: 0 | AL18: 0 | AM18: 0 | AN18: 0 | AO18: 0 | AP18: 0 | AQ18: 0 | AR18: 0 | AS18: 0 | AT18: 0 | AU18: 0 | AV18: 0 | AW18: 0 | AX18: 0 | AY18: 0 | AZ18: 0 | BA18: 0 | BB18: 0
A19: Amortization schedule
A20: Opening balance (kEUR) | C20: 0 | D20: 0 | E20: =C16 -> 24750 | F20: =E24 -> 24114.09 | G20: =F24 -> 23460.692 | H20: =G24 -> 22771.588 | I20: =H24 -> 22063.533 | J20: =I24 -> 21317.995 | K20: =J24 -> 20551.955 | L20: =K24 -> 19746.561 | M20: =L24 -> 18919.018 | ... AH20: =AG24 -> 0 | AI20: 0 | AJ20: 0 | AK20: 0 | AL20: 0 | AM20: 0 | AN20: 0 | AO20: 0 | AP20: 0 | AQ20: 0 | AR20: 0 | AS20: 0 | AT20: 0 | AU20: 0 | AV20: 0 | AW20: 0 | AX20: 0 | AY20: 0 | AZ20: 0 | BA20: 0 | BB20: 0
A21: Interest (kEUR) | C21: 0 | D21: 0 | E21: =E20*('Inputs'!$C$30+'Inputs'!$C$31/10000)/2 -> 680.625 | F21: =F20*('Inputs'!$C$30+'Inputs'!$C$31/10000)/2 -> 663.13747 | G21: =G20*('Inputs'!$C$30+'Inputs'!$C$31/10000)/2 -> 645.16903 | H21: =H20*('Inputs'!$C$30+'Inputs'!$C$31/10000)/2 -> 626.21866 | I21: =I20*('Inputs'!$C$30+'Inputs'!$C$31/10000)/2 -> 606.74715 | J21: =J20*('Inputs'!$C$30+'Inputs'!$C$31/10000)/2 -> 586.24486 | K21: =K20*('Inputs'!$C$30+'Inputs'!$C$31/10000)/2 -> 565.17876 | L21: =L20*('Inputs'!$C$30+'Inputs'!$C$31/10000)/2 -> 543.03042 | ... AH21: =AH20*('Inputs'!$C$30+'Inputs'!$C$31/10000)/2 -> 0 | AI21: 0 | AJ21: 0 | AK21: 0 | AL21: 0 | AM21: 0 | AN21: 0 | AO21: 0 | AP21: 0 | AQ21: 0 | AR21: 0 | AS21: 0 | AT21: 0 | AU21: 0 | AV21: 0 | AW21: 0 | AX21: 0 | AY21: 0 | AZ21: 0 | BA21: 0 | BB21: 0
A22: Senior debt service (kEUR) | C22: 0 | D22: 0 | E22: =MIN(E18,E20+E21) | F22: =MIN(F18,F20+F21) | G22: =MIN(G18,G20+G21) | H22: =MIN(H18,H20+H21) | I22: =MIN(I18,I20+I21) | J22: =MIN(J18,J20+J21) | K22: =MIN(K18,K20+K21) | L22: =MIN(L18,L20+L21) | ... AG22: =MIN(AG18,AG20+AG21) | AH22: =AH23+AH21 -> 0 | AI22: 0 | AJ22: 0 | AK22: 0 | AL22: 0 | AM22: 0 | AN22: 0 | AO22: 0 | AP22: 0 | AQ22: 0 | AR22: 0 | AS22: 0 | AT22: 0 | AU22: 0 | AV22: 0 | AW22: 0 | AX22: 0 | AY22: 0 | AZ22: 0 | BA22: 0 | BB22: 0
A23: Principal (kEUR) | C23: 0 | D23: 0 | E23: =E22-E21 -> 635.91016 | F23: =F22-F21 -> 653.39769 | G23: =G22-G21 -> 689.10461 | H23: =H22-H21 -> 708.05499 | I23: =I22-I21 -> 745.5377 | J23: =J22-J21 -> 766.03998 | K23: =K22-K21 -> 805.39413 | L23: =L22-L21 -> 827.54247 | ... AG23: =AG22-AG21 -> 0 | AH23: =AH20 -> 0 | AI23: 0 | AJ23: 0 | AK23: 0 | AL23: 0 | AM23: 0 | AN23: 0 | AO23: 0 | AP23: 0 | AQ23: 0 | AR23: 0 | AS23: 0 | AT23: 0 | AU23: 0 | AV23: 0 | AW23: 0 | AX23: 0 | AY23: 0 | AZ23: 0 | BA23: 0 | BB23: 0
A24: Closing balance (kEUR) | C24: 0 | D24: 0 | E24: =E20-E23 -> 24114.09 | F24: =F20-F23 -> 23460.692 | G24: =G20-G23 -> 22771.588 | H24: =H20-H23 -> 22063.533 | I24: =I20-I23 -> 21317.995 | J24: =J20-J23 -> 20551.955 | K24: =K20-K23 -> 19746.561 | L24: =L20-L23 -> 18919.018 | ... AH24: =AH20-AH23 -> 0 | AI24: 0 | AJ24: 0 | AK24: 0 | AL24: 0 | AM24: 0 | AN24: 0 | AO24: 0 | AP24: 0 | AQ24: 0 | AR24: 0 | AS24: 0 | AT24: 0 | AU24: 0 | AV24: 0 | AW24: 0 | AX24: 0 | AY24: 0 | AZ24: 0 | BA24: 0 | BB24: 0
A25: DSCR (sizing proxy) | C25: n/a | D25: n/a | E25: =IF(E22=0,"n/a",E11/E22) -> 1.2 | F25: =IF(F22=0,"n/a",F11/F22) -> 1.2 | G25: =IF(G22=0,"n/a",G11/G22) -> 1.2 | H25: =IF(H22=0,"n/a",H11/H22) -> 1.2 | I25: =IF(I22=0,"n/a",I11/I22) -> 1.2 | J25: =IF(J22=0,"n/a",J11/J22) -> 1.2 | K25: =IF(K22=0,"n/a",K11/K22) -> 1.2 | L25: =IF(L22=0,"n/a",L11/L22) -> 1.2 | ... AH25: =IF(AH22=0,"n/a",AH11/AH22) -> n/a | AI25: n/a | AJ25: n/a | AK25: n/a | AL25: n/a | AM25: n/a | AN25: n/a | AO25: n/a | AP25: n/a | AQ25: n/a | AR25: n/a | AS25: n/a | AT25: n/a | AU25: n/a | AV25: n/a | AW25: n/a | AX25: n/a | AY25: n/a | AZ25: n/a | BA25: n/a | BB25: n/a

Sheet P&L
A1: Generic Solar PV — P&L
A3: Period | C3: P1 | D3: P2 | E3: P3 | F3: P4 | G3: P5 | H3: P6 | I3: P7 | J3: P8 | K3: P9 | L3: P10 | M3: P11 | N3: P12 | O3: P13 | P3: P14 | Q3: P15 | R3: P16 | S3: P17 | T3: P18 | U3: P19 | V3: P20 | W3: P21 | X3: P22 | Y3: P23 | Z3: P24 | AA3: P25 | AB3: P26 | AC3: P27 | AD3: P28 | AE3: P29 | AF3: P30 | AG3: P31 | AH3: P32 | AI3: P33 | AJ3: P34 | AK3: P35 | AL3: P36 | AM3: P37 | AN3: P38 | AO3: P39 | AP3: P40 | AQ3: P41 | AR3: P42 | AS3: P43 | AT3: P44 | AU3: P45 | AV3: P46 | AW3: P47 | AX3: P48 | AY3: P49 | AZ3: P50 | BA3: P51 | BB3: P52
A5: Revenue | C5: ='Revenue'!C13 -> 0 | D5: ='Revenue'!D13 -> 0 | E5: ='Revenue'!E13 -> 2021.4562 | F5: ='Revenue'!F13 -> 2021.4562 | G5: ='Revenue'!G13 -> 2053.6378 | H5: ='Revenue'!H13 -> 2053.6378 | I5: ='Revenue'!I13 -> 2086.3317 | J5: ='Revenue'!J13 -> 2086.3317 | ... BB5: ='Revenue'!BB13 -> 3211.1424
A6: OpEx | C6: ='OpEx'!C10 -> 0 | D6: ='OpEx'!D10 -> 0 | E6: ='OpEx'!E10 -> 190 | F6: ='OpEx'!F10 -> 190 | G6: ='OpEx'!G10 -> 193.8 | H6: ='OpEx'!H10 -> 193.8 | I6: ='OpEx'!I10 -> 197.676 | J6: ='OpEx'!J10 -> 197.676 | ... BB6: ='OpEx'!BB10 -> 305.60308
A7: EBITDA | C7: =C5-C6 -> 0 | D7: =D5-D6 -> 0 | E7: =E5-E6 -> 1831.4562 | F7: =F5-F6 -> 1831.4562 | G7: =G5-G6 -> 1859.8378 | H7: =H5-H6 -> 1859.8378 | I7: =I5-I6 -> 1888.6557 | J7: =J5-J6 -> 1888.6557 | ... BB7: =BB5-BB6 -> 2905.5393
A8: Depreciation | C8: ='Debt Service'!C9 -> 0 | D8: ='Debt Service'!D9 -> 0 | E8: ='Debt Service'!E9 -> 825 | F8: ='Debt Service'!F9 -> 825 | G8: ='Debt Service'!G9 -> 825 | H8: ='Debt Service'!H9 -> 825 | I8: ='Debt Service'!I9 -> 825 | J8: ='Debt Service'!J9 -> 825 | ... BB8: ='Debt Service'!BB9 -> 0
A9: Interest expense (actual) | C9: ='Debt Service'!C21 -> 0 | D9: ='Debt Service'!D21 -> 0 | E9: ='Debt Service'!E21 -> 680.625 | F9: ='Debt Service'!F21 -> 663.13747 | G9: ='Debt Service'!G21 -> 645.16903 | H9: ='Debt Service'!H21 -> 626.21866 | I9: ='Debt Service'!I21 -> 606.74715 | J9: ='Debt Service'!J21 -> 586.24486 | ... BB9: ='Debt Service'!BB21 -> 0
A10: Pre-tax profit (EBITDA-Dep-Interest) | C10: =C7-C8-C9 -> 0 | D10: =D7-D8-D9 -> 0 | E10: =E7-E8-E9 -> 325.83125 | F10: =F7-F8-F9 -> 343.31878 | G10: =G7-G8-G9 -> 389.6688 | H10: =H7-H8-H9 -> 408.61918 | I10: =I7-I8-I9 -> 456.9086 | J10: =J7-J8-J9 -> 477.41089 | ... BB10: =BB7-BB8-BB9 -> 2905.5393
A11: Loss pool, opening | C11: 0 | D11: =C13 -> 0 | E11: =D13 -> 0 | F11: =E13 -> 0 | G11: =F13 -> 0 | H11: =G13 -> 0 | I11: =H13 -> 0 | J11: =I13 -> 0 | K11: =J13 -> 0 | ... BB11: =BA13 -> 0
A12: Loss pool used this period | C12: =IF(C10<0,0,MIN(C11,C10)) -> 0 | D12: =IF(D10<0,0,MIN(D11,D10)) -> 0 | E12: =IF(E10<0,0,MIN(E11,E10)) -> 0 | F12: =IF(F10<0,0,MIN(F11,F10)) -> 0 | G12: =IF(G10<0,0,MIN(G11,G10)) -> 0 | H12: =IF(H10<0,0,MIN(H11,H10)) -> 0 | I12: =IF(I10<0,0,MIN(I11,I10)) -> 0 | J12: =IF(J10<0,0,MIN(J11,J10)) -> 0 | ... BB12: =IF(BB10<0,0,MIN(BB11,BB10)) -> 0
A13: Loss pool, closing | C13: =C11-C12+IF(C10<0,-C10,0) -> 0 | D13: =D11-D12+IF(D10<0,-D10,0) -> 0 | E13: =E11-E12+IF(E10<0,-E10,0) -> 0 | F13: =F11-F12+IF(F10<0,-F10,0) -> 0 | G13: =G11-G12+IF(G10<0,-G10,0) -> 0 | H13: =H11-H12+IF(H10<0,-H10,0) -> 0 | I13: =I11-I12+IF(I10<0,-I10,0) -> 0 | J13: =J11-J12+IF(J10<0,-J10,0) -> 0 | ... BB13: =BB11-BB12+IF(BB10<0,-BB10,0) -> 0
A14: Taxable profit (after loss relief) | C14: =MAX(0,C10-C12) -> 0 | D14: =MAX(0,D10-D12) -> 0 | E14: =MAX(0,E10-E12) -> 325.83125 | F14: =MAX(0,F10-F12) -> 343.31878 | G14: =MAX(0,G10-G12) -> 389.6688 | H14: =MAX(0,H10-H12) -> 408.61918 | I14: =MAX(0,I10-I12) -> 456.9086 | J14: =MAX(0,J10-J12) -> 477.41089 | ... BB14: =MAX(0,BB10-BB12) -> 2905.5393
A15: Corporate tax | C15: =C14*'Inputs'!$C$33 -> 0 | D15: =D14*'Inputs'!$C$33 -> 0 | E15: =E14*'Inputs'!$C$33 -> 81.457812 | F15: =F14*'Inputs'!$C$33 -> 85.829695 | G15: =G14*'Inputs'!$C$33 -> 97.4172 | H15: =H14*'Inputs'!$C$33 -> 102.15479 | I15: =I14*'Inputs'!$C$33 -> 114.22715 | J15: =J14*'Inputs'!$C$33 -> 119.35272 | ... BB15: =BB14*'Inputs'!$C$33 -> 726.38483
A16: Net income | C16: =C10-C15 -> 0 | D16: =D10-D15 -> 0 | E16: =E10-E15 -> 244.37344 | F16: =F10-F15 -> 257.48908 | G16: =G10-G15 -> 292.2516 | H16: =H10-H15 -> 306.46438 | I16: =I10-I15 -> 342.68145 | J16: =J10-J15 -> 358.05817 | ... BB16: =BB10-BB15 -> 2179.1545

Sheet Cash Flow
A1: Generic Solar PV — Cash Flow
A3: Period | C3: P1 | D3: P2 | E3: P3 | F3: P4 | G3: P5 | H3: P6 | I3: P7 | J3: P8 | K3: P9 | L3: P10 | M3: P11 | N3: P12 | O3: P13 | P3: P14 | Q3: P15 | R3: P16 | S3: P17 | T3: P18 | U3: P19 | V3: P20 | W3: P21 | X3: P22 | Y3: P23 | Z3: P24 | AA3: P25 | AB3: P26 | AC3: P27 | AD3: P28 | AE3: P29 | AF3: P30 | AG3: P31 | AH3: P32 | AI3: P33 | AJ3: P34 | AK3: P35 | AL3: P36 | AM3: P37 | AN3: P38 | AO3: P39 | AP3: P40 | AQ3: P41 | AR3: P42 | AS3: P43 | AT3: P44 | AU3: P45 | AV3: P46 | AW3: P47 | AX3: P48 | AY3: P49 | AZ3: P50 | BA3: P51 | BB3: P52
A4: Period end date | C4: 47665 | D4: 47849 | E4: 48030 | F4: 48214 | G4: 48396 | H4: 48580 | I4: 48761 | J4: 48945 | K4: 49126 | L4: 49310 | M4: 49491 | N4: 49675 | O4: 49857 | P4: 50041 | Q4: 50222 | R4: 50406 | S4: 50587 | T4: 50771 | U4: 50952 | V4: 51136 | W4: 51318 | X4: 51502 | Y4: 51683 | Z4: 51867 | AA4: 52048 | AB4: 52232 | AC4: 52413 | AD4: 52597 | AE4: 52779 | AF4: 52963 | AG4: 53144 | AH4: 53328 | AI4: 53509 | AJ4: 53693 | AK4: 53874 | AL4: 54058 | AM4: 54240 | AN4: 54424 | AO4: 54605 | AP4: 54789 | AQ4: 54970 | AR4: 55154 | AS4: 55335 | AT4: 55519 | AU4: 55701 | AV4: 55885 | AW4: 56066 | AX4: 56250 | AY4: 56431 | AZ4: 56615 | BA4: 56796 | BB4: 56980
A6: Capex (construction, outflow) | C6: =-'CapEx'!C11 -> -17000 | D6: =-'CapEx'!D11 -> -16000 | E6: 0 | F6: 0 | G6: 0 | H6: 0 | I6: 0 | J6: 0 | K6: 0 | L6: 0 | M6: 0 | N6: 0 | O6: 0 | P6: 0 | Q6: 0 | R6: 0 | S6: 0 | T6: 0 | U6: 0 | V6: 0 | W6: 0 | X6: 0 | Y6: 0 | Z6: 0 | AA6: 0 | AB6: 0 | AC6: 0 | AD6: 0 | AE6: 0 | AF6: 0 | AG6: 0 | AH6: 0 | AI6: 0 | AJ6: 0 | AK6: 0 | AL6: 0 | AM6: 0 | AN6: 0 | AO6: 0 | AP6: 0 | AQ6: 0 | AR6: 0 | AS6: 0 | AT6: 0 | AU6: 0 | AV6: 0 | AW6: 0 | AX6: 0 | AY6: 0 | AZ6: 0 | BA6: 0 | BB6: 0
A7: EBITDA | C7: ='P&L'!C7 -> 0 | D7: ='P&L'!D7 -> 0 | E7: ='P&L'!E7 -> 1831.4562 | F7: ='P&L'!F7 -> 1831.4562 | G7: ='P&L'!G7 -> 1859.8378 | H7: ='P&L'!H7 -> 1859.8378 | I7: ='P&L'!I7 -> 1888.6557 | J7: ='P&L'!J7 -> 1888.6557 | ... BB7: ='P&L'!BB7 -> 2905.5393
A8: Tax | C8: ='P&L'!C15 -> 0 | D8: ='P&L'!D15 -> 0 | E8: ='P&L'!E15 -> 81.457812 | F8: ='P&L'!F15 -> 85.829695 | G8: ='P&L'!G15 -> 97.4172 | H8: ='P&L'!H15 -> 102.15479 | I8: ='P&L'!I15 -> 114.22715 | J8: ='P&L'!J15 -> 119.35272 | ... BB8: ='P&L'!BB15 -> 726.38483
A9: CFADS (true, = EBITDA - Tax) | C9: =C7-C8 -> 0 | D9: =D7-D8 -> 0 | E9: =E7-E8 -> 1749.9984 | F9: =F7-F8 -> 1745.6266 | G9: =G7-G8 -> 1762.4206 | H9: =H7-H8 -> 1757.683 | I9: =I7-I8 -> 1774.4286 | J9: =J7-J8 -> 1769.303 | ... BB9: =BB7-BB8 -> 2179.1545
A10: Senior debt service | C10: ='Debt Service'!C22 -> 0 | D10: ='Debt Service'!D22 -> 0 | E10: ='Debt Service'!E22 -> 1316.5352 | F10: ='Debt Service'!F22 -> 1316.5352 | G10: ='Debt Service'!G22 -> 1334.2736 | H10: ='Debt Service'!H22 -> 1334.2736 | I10: ='Debt Service'!I22 -> 1352.2848 | J10: ='Debt Service'!J22 -> 1352.2848 | ... BB10: ='Debt Service'!BB22 -> 0
A11: DSCR (true) | C11: =IF(C10=0,"n/a",C9/C10) -> n/a | D11: =IF(D10=0,"n/a",D9/D10) -> n/a | E11: =IF(E10=0,"n/a",E9/E10) -> 1.3292455 | F11: =IF(F10=0,"n/a",F9/F10) -> 1.3259248 | G11: =IF(G10=0,"n/a",G9/G10) -> 1.3208839 | H11: =IF(H10=0,"n/a",H9/H10) -> 1.3173333 | I11: =IF(I10=0,"n/a",I9/I10) -> 1.3121707 | J11: =IF(J10=0,"n/a",J9/J10) -> 1.3083804 | ... BB11: =IF(BB10=0,"n/a",BB9/BB10) -> n/a
A12: Unlevered project cash flow | C12: =C6+C9 -> -17000 | D12: =D6+D9 -> -16000 | E12: =E6+E9 -> 1749.9984 | F12: =F6+F9 -> 1745.6266 | G12: =G6+G9 -> 1762.4206 | H12: =H6+H9 -> 1757.683 | I12: =I6+I9 -> 1774.4286 | J12: =J6+J9 -> 1769.303 | ... BB12: =BB6+BB9 -> 2179.1545
A14: PROJECT IRR (XIRR) | C14: =XIRR(C12:BB12,C4:BB4) -> 0.10427402

Sheet Equity
A1: Generic Solar PV — Equity Cash Flow
A3: SHL and share capital are combined into a single equity cash flow series per the EQUITY_ONLY method. Senior debt drawn at COD returns capex already funded by equity during construction (construction debt = 0, see IDC tab).
A5: Period | C5: P1 | D5: P2 | E5: P3 | F5: P4 | G5: P5 | H5: P6 | I5: P7 | J5: P8 | K5: P9 | L5: P10 | M5: P11 | N5: P12 | O5: P13 | P5: P14 | Q5: P15 | R5: P16 | S5: P17 | T5: P18 | U5: P19 | V5: P20 | W5: P21 | X5: P22 | Y5: P23 | Z5: P24 | AA5: P25 | AB5: P26 | AC5: P27 | AD5: P28 | AE5: P29 | AF5: P30 | AG5: P31 | AH5: P32 | AI5: P33 | AJ5: P34 | AK5: P35 | AL5: P36 | AM5: P37 | AN5: P38 | AO5: P39 | AP5: P40 | AQ5: P41 | AR5: P42 | AS5: P43 | AT5: P44 | AU5: P45 | AV5: P46 | AW5: P47 | AX5: P48 | AY5: P49 | AZ5: P50 | BA5: P51 | BB5: P52
A6: Period end date | C6: 47665 | D6: 47849 | E6: 48030 | F6: 48214 | G6: 48396 | H6: 48580 | I6: 48761 | J6: 48945 | K6: 49126 | L6: 49310 | M6: 49491 | N6: 49675 | O6: 49857 | P6: 50041 | Q6: 50222 | R6: 50406 | S6: 50587 | T6: 50771 | U6: 50952 | V6: 51136 | W6: 51318 | X6: 51502 | Y6: 51683 | Z6: 51867 | AA6: 52048 | AB6: 52232 | AC6: 52413 | AD6: 52597 | AE6: 52779 | AF6: 52963 | AG6: 53144 | AH6: 53328 | AI6: 53509 | AJ6: 53693 | AK6: 53874 | AL6: 54058 | AM6: 54240 | AN6: 54424 | AO6: 54605 | AP6: 54789 | AQ6: 54970 | AR6: 55154 | AS6: 55335 | AT6: 55519 | AU6: 55701 | AV6: 55885 | AW6: 56066 | AX6: 56250 | AY6: 56431 | AZ6: 56615 | BA6: 56796 | BB6: 56980
A8: Equity capex contribution (outflow) | C8: =-'CapEx'!C11 -> -17000 | D8: =-'CapEx'!D11 -> -16000 | E8: 0 | F8: 0 | G8: 0 | H8: 0 | I8: 0 | J8: 0 | K8: 0 | L8: 0 | M8: 0 | N8: 0 | O8: 0 | P8: 0 | Q8: 0 | R8: 0 | S8: 0 | T8: 0 | U8: 0 | V8: 0 | W8: 0 | X8: 0 | Y8: 0 | Z8: 0 | AA8: 0 | AB8: 0 | AC8: 0 | AD8: 0 | AE8: 0 | AF8: 0 | AG8: 0 | AH8: 0 | AI8: 0 | AJ8: 0 | AK8: 0 | AL8: 0 | AM8: 0 | AN8: 0 | AO8: 0 | AP8: 0 | AQ8: 0 | AR8: 0 | AS8: 0 | AT8: 0 | AU8: 0 | AV8: 0 | AW8: 0 | AX8: 0 | AY8: 0 | AZ8: 0 | BA8: 0 | BB8: 0
A9: Senior debt draw at COD (return of capital) | C9: 0 | D9: 0 | E9: ='Debt Service'!$C$16 -> 24750 | F9: 0 | G9: 0 | H9: 0 | I9: 0 | J9: 0 | K9: 0 | L9: 0 | M9: 0 | N9: 0 | O9: 0 | P9: 0 | Q9: 0 | R9: 0 | S9: 0 | T9: 0 | U9: 0 | V9: 0 | W9: 0 | X9: 0 | Y9: 0 | Z9: 0 | AA9: 0 | AB9: 0 | AC9: 0 | AD9: 0 | AE9: 0 | AF9: 0 | AG9: 0 | AH9: 0 | AI9: 0 | AJ9: 0 | AK9: 0 | AL9: 0 | AM9: 0 | AN9: 0 | AO9: 0 | AP9: 0 | AQ9: 0 | AR9: 0 | AS9: 0 | AT9: 0 | AU9: 0 | AV9: 0 | AW9: 0 | AX9: 0 | AY9: 0 | AZ9: 0 | BA9: 0 | BB9: 0
A10: Distributions (CFADS - debt service, 100% sweep) | C10: 0 | D10: 0 | E10: =MAX(0,'Cash Flow'!E9-'Cash Flow'!E10) -> 433.46328 | F10: =MAX(0,'Cash Flow'!F9-'Cash Flow'!F10) -> 429.0914 | G10: =MAX(0,'Cash Flow'!G9-'Cash Flow'!G10) -> 428.14699 | H10: =MAX(0,'Cash Flow'!H9-'Cash Flow'!H10) -> 423.40939 | I10: =MAX(0,'Cash Flow'!I9-'Cash Flow'!I10) -> 422.14375 | J10: =MAX(0,'Cash Flow'!J9-'Cash Flow'!J10) -> 417.01818 | K10: =MAX(0,'Cash Flow'!K9-'Cash Flow'!K10) -> 415.40927 | L10: =MAX(0,'Cash Flow'!L9-'Cash Flow'!L10) -> 409.87218 | ... BB10: =MAX(0,'Cash Flow'!BB9-'Cash Flow'!BB10) -> 2179.1545
A11: Total equity cash flow | C11: =C8+C9+C10 -> -17000 | D11: =D8+D9+D10 -> -16000 | E11: =E8+E9+E10 -> 25183.463 | F11: =F8+F9+F10 -> 429.0914 | G11: =G8+G9+G10 -> 428.14699 | H11: =H8+H9+H10 -> 423.40939 | I11: =I8+I9+I10 -> 422.14375 | J11: =J8+J9+J10 -> 417.01818 | ... BB11: =BB8+BB9+BB10 -> 2179.1545
A13: EQUITY IRR (XIRR) | C13: =XIRR(C11:BB11,C6:BB6) -> 0.13184734

Sheet Summary
A1: GENERIC SOLAR PV — REFERENCE MODEL SUMMARY
A2: Source: External independent reference Excel (G1A-SPEC validation pack)
A4: KPI | B4: Unit | C4: Value | D4: Source sheet | E4: Source cell | F4: Note
A5: total_revenue_keur | B5: kEUR | C5: ='Revenue'!$C$15 -> 129903.91 | D5: Revenue | E5: 'Revenue'!$C$15 | F5: Sum of all period total revenue
A6: total_opex_keur | B6: kEUR | C6: ='OpEx'!$C$12 -> 12171.514 | D6: OpEx | E6: 'OpEx'!$C$12 | F6: Sum of all period total opex
A7: total_ebitda_keur | B7: kEUR | C7: =SUM('P&L'!C7:BB7) -> 117732.39 | D7: P&L | E7: C7:BB7 | F7: Sum of period EBITDA
A8: total_capex_keur | B8: kEUR | C8: ='CapEx'!$BD$11 -> 33000 | D8: CapEx | E8: 'CapEx'!$BD$11 | F8: Hard capex only (excl. IDC, fees)
A9: idc_keur | B9: kEUR | C9: ='IDC'!$C$30 -> 0 | D9: IDC | E9: 'IDC'!$C$30 | F9: Zero: no debt drawn during construction
A10: bank_fees_keur | B10: kEUR | C10: ='Inputs'!$C$36 -> 0 | D10: Inputs | E10: 'Inputs'!$C$36 | F10: Input assumption (0)
A11: senior_debt_keur | B11: kEUR | C11: ='Debt Service'!$C$16 -> 24750 | D11: Debt Service | E11: 'Debt Service'!$C$16 | F11: DSCR-sculpted, capped at gearing
A12: senior_debt_service_p1_keur | B12: kEUR | C12: ='Debt Service'!E22 -> 1316.5352 | D12: Debt Service | E12: E22 | F12: First operating period debt service
A13: senior_debt_service_p2_keur | B13: kEUR | C13: ='Debt Service'!F22 -> 1316.5352 | D13: Debt Service | E13: F22 | F13: Second operating period debt service
A14: senior_debt_service_p3_keur | B14: kEUR | C14: ='Debt Service'!G22 -> 1334.2736 | D14: Debt Service | E14: G22 | F14: Third operating period debt service
A15: avg_dscr | B15: x | C15: =AVERAGEIF('Cash Flow'!E11:BB11,">0") -> 1.2743553 | D15: Cash Flow | E15: E11:BB11 | F15: True CFADS / debt service, periods with debt service > 0
A16: min_dscr | B16: x | C16: =MIN('Cash Flow'!E11:BB11) -> 1.2130832 | D16: Cash Flow | E16: E11:BB11 | F16: Same range, minimum
A17: project_irr | B17: % | C17: ='Cash Flow'!$C$14 -> 0.10427402 | D17: Cash Flow | E17: 'Cash Flow'!$C$14 | F17: XIRR on unlevered project cash flow
A18: equity_irr | B18: % | C18: ='Equity'!$C$13 -> 0.13184734 | D18: Equity | E18: 'Equity'!$C$13 | F18: XIRR on combined equity cash flow
A19: realized_gearing | B19: % | C19: =C11/C8*100 -> 75 | D19: Summary | E19: C11/C8 | F19: senior_debt_keur / total_capex_keur

Sheet Methodology
A1: Generic Solar PV — Methodology
A3: MODELLING CONVENTIONS
A4: - Currency: all amounts in kEUR. Periods: semiannual (2 per year).
A5: - Construction periods precede COD; operating periods run for the full horizon after COD.
A6: - No VBA macros anywhere in this workbook. No external workbook links. No protected sheets.
A7: - Every cell on the Summary tab is a live formula chained back to the detail tabs; none are hardcoded.
A9: KEY SIMPLIFICATIONS / DEVIATIONS FROM THE NARRATIVE SPEC (documented per spec section 9):
A10: 1. CapEx spending-profile buckets ('Y0', 'Y1-H1', 'Y1-H2') are mapped directly, in order, onto the
A11: actual construction periods of each project (P1, P2, P3...) rather than literal calendar-year
A12: labels, because COD falls exactly at the start of the stated 'Y1', which makes a literal Y1-H1/H2
A13: construction spend impossible. Where a project has fewer construction periods than profile buckets
A14: (Solar: 2 periods vs Civil Works' 3 buckets), trailing buckets are folded into the last construction period.
... A47: - Rounding convention: 0dp on kEUR amounts, 4dp on ratios, 6dp on IRRs (display only; underlying values unrounded).
